{
	"info": {
		"_postman_id": "083ce1b3-e268-492f-8f7c-ca690d19acba",
		"name": "RestfulGloom",
		"schema": "https://schema.getpostman.com/json/collection/v2.1.0/collection.json"
	},
	"item": [
		{
			"name": "api",
			"item": [
				{
					"name": "v1",
					"item": [],
					"_postman_isSubFolder": true
				},
				{
					"name": "dev",
					"item": [
						{
							"name": "/login/dev",
							"request": {
								"auth": {
									"type": "noauth"
								},
								"method": "POST",
								"header": [],
								"body": {
									"mode": "raw",
									"raw": ""
								},
								"url": {
									"raw": "{{base_url}}/api/dev/login?name=mike",
									"host": [
										"{{base_url}}"
									],
									"path": [
										"api",
										"dev",
										"login"
									],
									"query": [
										{
											"key": "name",
											"value": "mike"
										},
										{
											"key": "role",
											"value": "User",
											"disabled": true
										}
									]
								}
							},
							"response": []
						}
					],
					"_postman_isSubFolder": true
				},
				{
					"name": "/",
					"request": {
						"auth": {
							"type": "noauth"
						},
						"method": "GET",
						"header": [
							{
								"key": "Authorization",
								"value": "{{token}}",
								"type": "text"
							}
						],
						"body": {
							"mode": "raw",
							"raw": ""
						},
						"url": {
							"raw": "{{base_url}}/api",
							"host": [
								"{{base_url}}"
							],
							"path": [
								"api"
							]
						}
					},
					"response": []
				}
			],
			"auth": {
				"type": "bearer",
				"bearer": [
					{
						"key": "token",
						"value": "{{token}}",
						"type": "string"
					}
				]
			},
			"event": [
				{
					"listen": "prerequest",
					"script": {
						"id": "277b6965-9c35-4487-8eb6-a9da1573f431",
						"type": "text/javascript",
						"exec": [
							""
						]
					}
				},
				{
					"listen": "test",
					"script": {
						"id": "f04617e8-aeb3-4bbd-9249-084e32dfa2da",
						"type": "text/javascript",
						"exec": [
							""
						]
					}
				}
			]
		},
		{
			"name": "HTML pages",
			"item": [
				{
					"name": "/",
					"request": {
						"method": "GET",
						"header": [],
						"body": {
							"mode": "raw",
							"raw": ""
						},
						"url": {
							"raw": "{{base_url}}/",
							"host": [
								"{{base_url}}"
							],
							"path": [
								""
							]
						}
					},
					"response": []
				},
				{
					"name": "/hello",
					"request": {
						"method": "GET",
						"header": [],
						"body": {
							"mode": "raw",
							"raw": ""
						},
						"url": {
							"raw": "{{base_url}}/hello",
							"host": [
								"{{base_url}}"
							],
							"path": [
								"hello"
							]
						}
					},
					"response": []
				},
				{
					"name": "/home",
					"request": {
						"method": "GET",
						"header": [],
						"body": {
							"mode": "raw",
							"raw": ""
						},
						"url": {
							"raw": "{{base_url}}/home",
							"host": [
								"{{base_url}}"
							],
							"path": [
								"home"
							]
						}
					},
					"response": []
				},
				{
					"name": "/registration",
					"request": {
						"method": "GET",
						"header": [],
						"body": {
							"mode": "raw",
							"raw": ""
						},
						"url": {
							"raw": "{{base_url}}/registration",
							"host": [
								"{{base_url}}"
							],
							"path": [
								"registration"
							]
						}
					},
					"response": []
				}
			]
		},
		{
			"name": "login",
			"item": [
				{
					"name": "/login",
					"request": {
						"method": "GET",
						"header": [],
						"body": {
							"mode": "raw",
							"raw": ""
						},
						"url": {
							"raw": "{{base_url}}/login",
							"host": [
								"{{base_url}}"
							],
							"path": [
								"login"
							]
						}
					},
					"response": []
				},
				{
					"name": "/login",
					"request": {
						"method": "POST",
						"header": [],
						"body": {
							"mode": "formdata",
							"formdata": [
								{
									"key": "username",
									"value": "admin",
									"type": "text"
								},
								{
									"key": "password",
									"value": "admin",
									"type": "text"
								}
							]
						},
						"url": {
							"raw": "{{base_url}}/login",
							"host": [
								"{{base_url}}"
							],
							"path": [
								"login"
							]
						}
					},
					"response": []
				}
			],
			"auth": {
				"type": "noauth"
			}
		}
	]
}
